[
    {
        "schematic": false,
        "sex": false,
        "violence": false,
        "aac": false,
        "aacColor": false,
        "skin": true,
        "hair": true,
        "downloads": 0,
        "categories": [
            "personal pronoun"
        ],
        "synsets": [],
        "tags": [
            "communication",
            "language",
            "pronoun",
            "personal pronoun"
        ],
        "_id": 31807,
        "created": "2017-12-04T13:26:23.000Z",
        "lastUpdated": "2020-11-12T11:54:24.810Z",
        "keywords": [
            {
                "type": 6,
                "keyword": "io",
                "hasLocution": true
            },
            {
                "type": 6,
                "keyword": "mi",
                "hasLocution": true
            }
        ],
        "desc": "",
        "url": "https://static.arasaac.org/pictograms/31807/31807_hair-ED4120_skin-F5E5DE_500.png",
        "word": "io"
    },
    {
        "schematic": false,
        "sex": false,
        "violence": false,
        "aac": false,
        "aacColor": false,
        "skin": true,
        "hair": true,
        "downloads": 0,
        "categories": [
            "personal pronoun"
        ],
        "synsets": [],
        "tags": [
            "communication",
            "language",
            "pronoun",
            "personal pronoun"
        ],
        "_id": 31801,
        "created": "2017-12-04T13:23:29.000Z",
        "lastUpdated": "2020-11-12T11:55:27.833Z",
        "keywords": [
            {
                "type": 6,
                "keyword": "tu",
                "hasLocution": true
            },
            {
                "type": 6,
                "keyword": "voi",
                "hasLocution": true
            },
            {
                "keyword": "Lei",
                "hasLocution": true,
                "type": 6
            }
        ],
        "desc": "",
        "url": "https://static.arasaac.org/pictograms/31801/31801_hair-ED4120_skin-F5E5DE_500.png",
        "word": "tu"
    },
    {
        "schematic": false,
        "sex": false,
        "violence": false,
        "aac": false,
        "aacColor": false,
        "skin": true,
        "hair": true,
        "downloads": 0,
        "categories": [
            "personal pronoun"
        ],
        "synsets": [
            ""
        ],
        "tags": [
            "communication",
            "language",
            "pronoun",
            "personal pronoun"
        ],
        "_id": 6480,
        "created": "2008-12-01T13:11:53.000Z",
        "lastUpdated": "2020-11-16T18:59:54.477Z",
        "keywords": [
            {
                "type": 1,
                "keyword": "egli",
                "hasLocution": true
            },
            {
                "type": 1,
                "keyword": "lui",
                "hasLocution": true
            }
        ],
        "desc": "",
        "url": "https://static.arasaac.org/pictograms/6480/6480_hair-ED4120_skin-F5E5DE_500.png",
        "word": "egli"
    },
    {
        "schematic": false,
        "sex": false,
        "violence": false,
        "aac": false,
        "aacColor": false,
        "skin": true,
        "hair": true,
        "downloads": 0,
        "categories": [
            "personal pronoun"
        ],
        "synsets": [
            ""
        ],
        "tags": [
            "communication",
            "language",
            "pronoun",
            "personal pronoun"
        ],
        "_id": 31672,
        "created": "2017-12-01T11:49:53.000Z",
        "lastUpdated": "2020-11-12T16:17:42.734Z",
        "keywords": [
            {
                "type": 6,
                "keyword": "noi",
                "hasLocution": true
            }
        ],
        "desc": "",
        "url": "https://static.arasaac.org/pictograms/31672/31672_hair-ED4120_skin-F5E5DE_500.png",
        "word": "noi"
    },
    {
        "schematic": false,
        "sex": false,
        "violence": false,
        "aac": false,
        "aacColor": false,
        "skin": true,
        "hair": true,
        "downloads": 0,
        "categories": [
            "personal pronoun"
        ],
        "synsets": [],
        "tags": [
            "communication",
            "language",
            "pronoun",
            "personal pronoun"
        ],
        "_id": 7306,
        "created": "2009-01-22T11:34:57.000Z",
        "lastUpdated": "2021-01-20T07:52:23.682Z",
        "keywords": [
            {
                "type": 1,
                "keyword": "voi",
                "hasLocution": true
            }
        ],
        "desc": "",
        "url": "https://static.arasaac.org/pictograms/7306/7306_hair-ED4120_skin-F5E5DE_500.png",
        "word": "voi"
    },
    {
        "schematic": false,
        "sex": false,
        "violence": false,
        "aac": false,
        "aacColor": false,
        "skin": true,
        "hair": true,
        "downloads": 0,
        "categories": [
            "personal pronoun"
        ],
        "synsets": [],
        "tags": [
            "communication",
            "language",
            "pronoun",
            "personal pronoun"
        ],
        "_id": 7032,
        "created": "2009-01-13T11:24:00.000Z",
        "lastUpdated": "2021-01-19T10:13:27.542Z",
        "keywords": [
            {
                "type": 1,
                "keyword": "loro",
                "hasLocution": true
            },
            {
                "type": 1,
                "keyword": "essi",
                "hasLocution": true
            },
            {
                "keyword": "si",
                "hasLocution": true,
                "type": 6
            },
            {
                "keyword": "gli",
                "hasLocution": true,
                "type": 1
            }
        ],
        "desc": "",
        "url": "https://static.arasaac.org/pictograms/7032/7032_hair-ED4120_skin-F5E5DE_500.png",
        "word": "loro"
    }
]